senseye_cameras/__init__.py
senseye_cameras/loop_thread.py
senseye_cameras/reader.py
senseye_cameras/safe_queue.py
senseye_cameras/stream.py
senseye_cameras/writer.py
senseye_cameras/input/__init__.py
senseye_cameras/input/camera_ffmpeg.py
senseye_cameras/input/camera_pylon.py
senseye_cameras/input/camera_raw_video.py
senseye_cameras/input/camera_ueye.py
senseye_cameras/input/camera_usb.py
senseye_cameras/input/input.py
senseye_cameras/input/input_factory.py
senseye_cameras/input/microphone.py
senseye_cameras/output/__init__.py
senseye_cameras/output/audio_file.py
senseye_cameras/output/file.py
senseye_cameras/output/h264_pipe.py
senseye_cameras/output/output.py
senseye_cameras/output/output_factory.py
senseye_cameras/output/video_file.py
senseye_cameras-1.1.0.dist-info/LICENSE
senseye_cameras-1.1.0.dist-info/METADATA
senseye_cameras-1.1.0.dist-info/WHEEL
senseye_cameras-1.1.0.dist-info/top_level.txt
senseye_cameras-1.1.0.dist-info/RECORD
