Metadata-Version: 2.1
Name: senseye-cameras
Version: 1.1.0
Summary: Senseye Camera Utilities
Home-page: https://github.com/senseye-inc/senseye-cameras
Author: Senseye, Inc.
License: BSD-3-Clause
Project-URL: Download, https://github.com/senseye-inc/senseye-cameras/releases
Project-URL: Source Code, https://github.com/senseye-inc/senseye-cameras
Project-URL: Documentation, https://senseye-cameras.readthedocs.io/en/latest/
Project-URL: Homepage, http://senseye.co/
Platform: UNKNOWN
Requires-Dist: numpy (>=1.14.5)
Requires-Dist: opencv-python-headless (>=4.4.0.46)
Requires-Dist: ffmpeg-python (>=0.2.0)
Requires-Dist: senseye-pyueye (>=0.2.0)
Requires-Dist: sounddevice (>=0.3.14)
Requires-Dist: soundfile (>=0.10.3)
Provides-Extra: test
Requires-Dist: pytest ; extra == 'test'
